{
  "activeDeepening": {
    "apiErrors": 0,
    "coverageStatuses": [
      "api_review_capture_partial"
    ],
    "elapsedSeconds": 87.7,
    "estimatedRemainingSeconds": 0.0,
    "lastShop": "MasakiLong",
    "queuedCandidates": 50,
    "reviewRowsChanged": 4557,
    "reviewsFetched": 4557,
    "reviewsMissingListingMetadata": 0,
    "runStatus": "complete",
    "secondsPerShop": 1.8,
    "shopsCompleted": 50,
    "sourceFile": "backlog-partial-write.json",
    "updatedAt": "2026-06-13T19:52:05Z"
  },
  "activeWriterAlive": true,
  "coverageBacklog": {
    "capped": 0,
    "depthSatisfied": 144,
    "partial": 1953,
    "queued": 0,
    "queuedApiReviewCapture": 334,
    "queuedTotal": 334,
    "windowComplete": 18782
  },
  "currentPhase": "rollup_refresh_complete",
  "generatedAt": "2026-06-13T19:54:59Z",
  "latestQueryYield": {
    "generatedAt": "2026-06-13T19:39:01Z",
    "queryBank": "market_led_nameplates",
    "rateLimitErrors": 0,
    "reviewRowsWritten": 5904,
    "shopsPromoted": null
  },
  "nextSafeAction": "monitor active phase `rollup_refresh_complete`; avoid launching another SQL writer",
  "publicCommit": "9e180427f93f",
  "publish": {
    "lastReason": "thresholds not met: 243 new reviews since publish, 1168s elapsed, 2 runs",
    "lastStatus": "skipped",
    "lastStatusAt": "2026-06-13T19:38:48Z",
    "lastSuccessfulAt": "2026-06-13T19:16:22Z",
    "lastSuccessfulPublicCommit": "10ad641a6c72",
    "lastSuccessfulPublicDataReviewCount": 10234308,
    "lastSuccessfulReviewLedgerCount": 10234652
  },
  "rateLimitCooldown": {
    "active": false
  },
  "reviewLedgerCount": 10235068,
  "reviewListingMapping": {
    "cacheReviewDelta": 760,
    "dashboardGeneratedAt": "2026-06-13T15:09:22",
    "distinctListingUrls": 1906984,
    "gapDetailRows": 18,
    "reviewRows": 10234308,
    "rowsMissingListingMetadata": 18,
    "rowsMissingListingTitle": 18,
    "rowsMissingListingUrl": 0,
    "shopsMissingListingMetadata": 2,
    "source": "dashboard-cache"
  },
  "rollupFreshnessStatus": "current",
  "rollupSourceTotalReviews": 10235068,
  "rollupStaleReviewRows": 0
}
